picamera2_webstream/__init__.py
picamera2_webstream/stream_ffmpeg.py
picamera2_webstream/stream_picamera.py
picamera2_webstream-0.2.7.dist-info/LICENSE
picamera2_webstream-0.2.7.dist-info/METADATA
picamera2_webstream-0.2.7.dist-info/WHEEL
picamera2_webstream-0.2.7.dist-info/top_level.txt
picamera2_webstream-0.2.7.dist-info/RECORD
