Metadata-Version: 2.2
Name: picamera2-webstream
Version: 0.2.7
Summary: A Flask-based web streaming solution for Raspberry Pi cameras using PiCamera2
Author-email: Ian Ross Williams <ianrosswilliams@gmail.com>
License: MIT License
Project-URL: Homepage, https://github.com/GlassOnTin/picamera2-webstream
Project-URL: Repository, https://github.com/GlassOnTin/picamera2-webstream.git
Project-URL: Issues, https://github.com/GlassOnTin/picamera2-webstream/issues
Keywords: raspberry pi,camera,streaming,picamera2,ffmpeg,flask
Classifier: Development Status :: 4 - Beta
Classifier: Intended Audience :: Developers
Classifier: License :: OSI Approved :: MIT License
Classifier: Operating System :: POSIX :: Linux
Classifier: Programming Language :: Python :: 3
Classifier: Programming Language :: Python :: 3.7
Classifier: Programming Language :: Python :: 3.8
Classifier: Programming Language :: Python :: 3.9
Classifier: Topic :: Multimedia :: Video :: Capture
Requires-Python: >=3.7
License-File: LICENSE
Requires-Dist: flask>=2.0.0
